concept_sentinel_data_capturer/__init__.py
concept_sentinel_data_capturer/mappers.py
concept_sentinel_data_capturer/service.py
concept_sentinel_data_capturer-1.3.dist-info/METADATA
concept_sentinel_data_capturer-1.3.dist-info/WHEEL
concept_sentinel_data_capturer-1.3.dist-info/top_level.txt
concept_sentinel_data_capturer-1.3.dist-info/RECORD
