Metadata-Version: 2.4
Name: concept_sentinel_data_capturer
Version: 1.3
Summary: A python package to capture, monitor, store all data communications across agents and It further extracts key entities from the data which will be used to detect the behavioral changes of the agents
Requires-Dist: langchain==0.3.25
Requires-Dist: langchain-community==0.3.25
Requires-Dist: openai==1.97.1
Requires-Dist: pymongo==4.13.2
Requires-Dist: pydantic==2.11.5
Dynamic: description
Dynamic: description-content-type
Dynamic: requires-dist
Dynamic: summary
